safe_s3_storage/__init__.py
safe_s3_storage/exceptions.py
safe_s3_storage/file_validator.py
safe_s3_storage/kaspersky_scan_engine.py
safe_s3_storage/py.typed
safe_s3_storage/s3_service.py
safe_s3_storage-0.12.2.dist-info/WHEEL
safe_s3_storage-0.12.2.dist-info/METADATA
safe_s3_storage-0.12.2.dist-info/RECORD
