Metadata-Version: 2.3
Name: safe-s3-storage
Version: 0.12.2
Summary: S3 safe storage
Keywords: s3,kaspersky,antivirus,upload
Author: community-of-python
Classifier: Natural Language :: English
Classifier: Programming Language :: Python :: 3.10
Classifier: Programming Language :: Python :: 3.11
Classifier: Programming Language :: Python :: 3.12
Classifier: Programming Language :: Python :: 3.13
Classifier: Programming Language :: Python :: 3.14
Classifier: Topic :: Software Development :: Libraries
Classifier: Topic :: Communications :: File Sharing
Classifier: Typing :: Typed
Requires-Dist: httpx
Requires-Dist: aioboto3
Requires-Dist: types-aioboto3[s3]
Requires-Dist: pydantic
Requires-Dist: pyvips
Requires-Dist: pyvips-binary<=8.17.3
Requires-Dist: python-magic
Requires-Python: >=3.10
